{"campaign_id":"sun-cheng-yaw-ata-2013-11-22-1","events":[{"event_id":"sun-cheng-yaw-ata-2013-11-22-1-stake-disclosure-2013-11-22-1","campaign_id":"sun-cheng-yaw-ata-2013-11-22-1","event_type":"stake_disclosure","event_date":"2013-11-22","actor_side":"activist","materiality_score":98,"is_material_node":true,"previous_event_id":null,"trigger_event_id":null,"artifacts":[{"artifact_id":"277d51f7e65d","campaign_id":"sun-cheng-yaw-ata-2013-11-22-1","event_id":"sun-cheng-yaw-ata-2013-11-22-1-stake-disclosure-2013-11-22-1","artifact_type":"filing","event_type":"stake_disclosure","evidence_rank":"primary_filing","source_url":"https://www.sec.gov/Archives/edgar/data/0001420529/000119312513450490/d633219dsc13d.htm","source_name":"sec_edgar_formtype","headline":"SCHEDULE 13D","published_at":"2013-11-22","dedup_cluster_id":"","attachment_confidence":1.0,"is_primary":true,"raw_id":"277d51f7e65d","form_type":"SC 13D","announcement_type":"","pdf_filename":"","blob_url":"","sector":"","title":"SCHEDULE 13D"}],"coverage_artifacts":[]},{"event_id":"sun-cheng-yaw-ata-2013-11-22-1-stake-disclosure-2019-02-15-2","campaign_id":"sun-cheng-yaw-ata-2013-11-22-1","event_type":"stake_disclosure","event_date":"2019-02-15","actor_side":"activist","materiality_score":98,"is_material_node":true,"previous_event_id":"sun-cheng-yaw-ata-2013-11-22-1-stake-disclosure-2013-11-22-1","trigger_event_id":null,"artifacts":[{"artifact_id":"e931f1148f92","campaign_id":"sun-cheng-yaw-ata-2013-11-22-1","event_id":"sun-cheng-yaw-ata-2013-11-22-1-stake-disclosure-2019-02-15-2","artifact_type":"filing","event_type":"stake_disclosure","evidence_rank":"primary_filing","source_url":"https://www.sec.gov/Archives/edgar/data/0001420529/000119312519041947/d715033dsc13da.htm","source_name":"sec_edgar_formtype","headline":"SCHEDULE 13D AMENDMENT NO. 1","published_at":"2019-02-15","dedup_cluster_id":"","attachment_confidence":1.0,"is_primary":true,"raw_id":"e931f1148f92","form_type":"SC 13D/A","announcement_type":"","pdf_filename":"","blob_url":"","sector":"","title":"SCHEDULE 13D AMENDMENT NO. 1"}],"coverage_artifacts":[]}],"coverage_artifacts":[],"low_trust_artifacts":[]}