{"campaign_id":"elliott-cdk-global-undated-1","events":[{"event_id":"elliott-cdk-global-undated-1-activist-letter-undated-1","campaign_id":"elliott-cdk-global-undated-1","event_type":"activist_letter","event_date":"","actor_side":"activist","materiality_score":94,"is_material_node":true,"previous_event_id":null,"trigger_event_id":null,"artifacts":[{"artifact_id":"cdd5eccfc0ef","campaign_id":"elliott-cdk-global-undated-1","event_id":"elliott-cdk-global-undated-1-activist-letter-undated-1","artifact_type":"letter","event_type":"activist_letter","evidence_rank":"primary_fund","source_url":"https://www.10xebitda.com/wp-content/uploads/2016/12/Elliott-First-Letter-to-CDK-Global-May-2016.pdf","source_name":"10xebitda","headline":"Elliott First Letter to CDK Global","published_at":"","dedup_cluster_id":"","attachment_confidence":1.0,"is_primary":true,"raw_id":"cdd5eccfc0ef","form_type":"Shareholder Letter","announcement_type":"","pdf_filename":"cdd5eccfc0ef--elliott-management--cdk-global--.pdf","blob_url":"","sector":"","title":"Elliott First Letter to CDK Global"}],"coverage_artifacts":[]},{"event_id":"elliott-cdk-global-undated-1-activist-letter-undated-2","campaign_id":"elliott-cdk-global-undated-1","event_type":"activist_letter","event_date":"","actor_side":"activist","materiality_score":94,"is_material_node":true,"previous_event_id":"elliott-cdk-global-undated-1-activist-letter-undated-1","trigger_event_id":null,"artifacts":[{"artifact_id":"803bf962c92e","campaign_id":"elliott-cdk-global-undated-1","event_id":"elliott-cdk-global-undated-1-activist-letter-undated-2","artifact_type":"letter","event_type":"activist_letter","evidence_rank":"primary_fund","source_url":"https://www.10xebitda.com/wp-content/uploads/2016/12/Elliott-Second-Letter-to-CDK-Global-Jun-2016.pdf","source_name":"10xebitda","headline":"Elliott Second Letter to CDK Global","published_at":"","dedup_cluster_id":"","attachment_confidence":1.0,"is_primary":true,"raw_id":"803bf962c92e","form_type":"Shareholder Letter","announcement_type":"","pdf_filename":"803bf962c92e--elliott-management--cdk-global--.pdf","blob_url":"","sector":"","title":"Elliott Second Letter to CDK Global"}],"coverage_artifacts":[]}],"coverage_artifacts":[],"low_trust_artifacts":[]}