{"campaign_id":"lone-star-swss-2014-08-18-1","events":[{"event_id":"lone-star-swss-2014-08-18-1-stake-disclosure-2014-08-18-1","campaign_id":"lone-star-swss-2014-08-18-1","event_type":"stake_disclosure","event_date":"2014-08-18","actor_side":"activist","materiality_score":98,"is_material_node":true,"previous_event_id":null,"trigger_event_id":null,"artifacts":[{"artifact_id":"fd485c611bf1","campaign_id":"lone-star-swss-2014-08-18-1","event_id":"lone-star-swss-2014-08-18-1-stake-disclosure-2014-08-18-1","artifact_type":"filing","event_type":"stake_disclosure","evidence_rank":"primary_filing","source_url":"https://www.sec.gov/Archives/edgar/data/0000878520/000141588914002542/sc13d09482004_08152014.htm","source_name":"sec_edgar_formtype","headline":"SCHEDULE 13D","published_at":"2014-08-18","dedup_cluster_id":"","attachment_confidence":1.0,"is_primary":true,"raw_id":"fd485c611bf1","form_type":"SC 13D","announcement_type":"","pdf_filename":"","blob_url":"","sector":"","title":"SCHEDULE 13D"},{"artifact_id":"a51943393c8a","campaign_id":"lone-star-swss-2014-08-18-1","event_id":"lone-star-swss-2014-08-18-1-stake-disclosure-2014-08-18-1","artifact_type":"filing","event_type":"stake_disclosure","evidence_rank":"primary_filing","source_url":"https://www.sec.gov/Archives/edgar/data/0000878520/000092189514001925/sc13da109482004_08192014.htm","source_name":"sec_edgar_formtype","headline":"AMENDMENT NO. 1 TO THE SCHEDULE 13D","published_at":"2014-08-21","dedup_cluster_id":"","attachment_confidence":1.0,"is_primary":true,"raw_id":"a51943393c8a","form_type":"SC 13D/A","announcement_type":"","pdf_filename":"","blob_url":"","sector":"","title":"AMENDMENT NO. 1 TO THE SCHEDULE 13D"}],"coverage_artifacts":[]},{"event_id":"lone-star-swss-2014-08-18-1-stake-disclosure-2014-08-26-2","campaign_id":"lone-star-swss-2014-08-18-1","event_type":"stake_disclosure","event_date":"2014-08-26","actor_side":"activist","materiality_score":98,"is_material_node":true,"previous_event_id":"lone-star-swss-2014-08-18-1-stake-disclosure-2014-08-18-1","trigger_event_id":null,"artifacts":[{"artifact_id":"8e471d3d0c2c","campaign_id":"lone-star-swss-2014-08-18-1","event_id":"lone-star-swss-2014-08-18-1-stake-disclosure-2014-08-26-2","artifact_type":"filing","event_type":"stake_disclosure","evidence_rank":"primary_filing","source_url":"https://www.sec.gov/Archives/edgar/data/0000878520/000092189514001948/sc13da209482004_08222014.htm","source_name":"sec_edgar_formtype","headline":"AMENDMENT NO. 2 TO THE SCHEDULE 13D","published_at":"2014-08-26","dedup_cluster_id":"","attachment_confidence":1.0,"is_primary":true,"raw_id":"8e471d3d0c2c","form_type":"SC 13D/A","announcement_type":"","pdf_filename":"","blob_url":"","sector":"","title":"AMENDMENT NO. 2 TO THE SCHEDULE 13D"},{"artifact_id":"41a2bb846e12","campaign_id":"lone-star-swss-2014-08-18-1","event_id":"lone-star-swss-2014-08-18-1-stake-disclosure-2014-08-26-2","artifact_type":"filing","event_type":"stake_disclosure","evidence_rank":"primary_filing","source_url":"https://www.sec.gov/Archives/edgar/data/0000878520/000092189514001972/sc13da309482004_08272014.htm","source_name":"sec_edgar_formtype","headline":"AMENDMENT NO. 3 TO THE SCHEDULE 13D","published_at":"2014-09-02","dedup_cluster_id":"","attachment_confidence":1.0,"is_primary":true,"raw_id":"41a2bb846e12","form_type":"SC 13D/A","announcement_type":"","pdf_filename":"","blob_url":"","sector":"","title":"AMENDMENT NO. 3 TO THE SCHEDULE 13D"}],"coverage_artifacts":[]},{"event_id":"lone-star-swss-2014-08-18-1-stake-disclosure-2014-10-06-3","campaign_id":"lone-star-swss-2014-08-18-1","event_type":"stake_disclosure","event_date":"2014-10-06","actor_side":"activist","materiality_score":98,"is_material_node":true,"previous_event_id":"lone-star-swss-2014-08-18-1-stake-disclosure-2014-08-26-2","trigger_event_id":null,"artifacts":[{"artifact_id":"ede2d48dd259","campaign_id":"lone-star-swss-2014-08-18-1","event_id":"lone-star-swss-2014-08-18-1-stake-disclosure-2014-10-06-3","artifact_type":"filing","event_type":"stake_disclosure","evidence_rank":"primary_filing","source_url":"https://www.sec.gov/Archives/edgar/data/0000878520/000092189514002172/sc13da409482004_10032014.htm","source_name":"sec_edgar_formtype","headline":"AMENDMENT NO. 4 TO THE SCHEDULE 13D","published_at":"2014-10-06","dedup_cluster_id":"","attachment_confidence":1.0,"is_primary":true,"raw_id":"ede2d48dd259","form_type":"SC 13D/A","announcement_type":"","pdf_filename":"","blob_url":"","sector":"","title":"AMENDMENT NO. 4 TO THE SCHEDULE 13D"}],"coverage_artifacts":[]}],"coverage_artifacts":[],"low_trust_artifacts":[]}