{"campaign_id":"wb-co-castle-a-m-2013-03-01-1","events":[{"event_id":"wb-co-castle-a-m-2013-03-01-1-stake-disclosure-2013-03-01-1","campaign_id":"wb-co-castle-a-m-2013-03-01-1","event_type":"stake_disclosure","event_date":"2013-03-01","actor_side":"activist","materiality_score":98,"is_material_node":true,"previous_event_id":null,"trigger_event_id":null,"artifacts":[{"artifact_id":"0cbe9e3fdba5","campaign_id":"wb-co-castle-a-m-2013-03-01-1","event_id":"wb-co-castle-a-m-2013-03-01-1-stake-disclosure-2013-03-01-1","artifact_type":"filing","event_type":"stake_disclosure","evidence_rank":"primary_filing","source_url":"https://www.sec.gov/Archives/edgar/data/0000018172/000091476013000030/a05104_sc13da6.htm","source_name":"sec_edgar_formtype","headline":"AMENDMENT NO. 6","published_at":"2013-03-01","dedup_cluster_id":"","attachment_confidence":1.0,"is_primary":true,"raw_id":"0cbe9e3fdba5","form_type":"SC 13D/A","announcement_type":"","pdf_filename":"","sector":"","title":"AMENDMENT NO. 6"}],"coverage_artifacts":[]},{"event_id":"wb-co-castle-a-m-2013-03-01-1-stake-disclosure-2013-06-24-2","campaign_id":"wb-co-castle-a-m-2013-03-01-1","event_type":"stake_disclosure","event_date":"2013-06-24","actor_side":"activist","materiality_score":98,"is_material_node":true,"previous_event_id":"wb-co-castle-a-m-2013-03-01-1-stake-disclosure-2013-03-01-1","trigger_event_id":null,"artifacts":[{"artifact_id":"c82600db2b18","campaign_id":"wb-co-castle-a-m-2013-03-01-1","event_id":"wb-co-castle-a-m-2013-03-01-1-stake-disclosure-2013-06-24-2","artifact_type":"filing","event_type":"stake_disclosure","evidence_rank":"primary_filing","source_url":"https://www.sec.gov/Archives/edgar/data/0000018172/000091476013000047/a05104_sc13da7.htm","source_name":"sec_edgar_formtype","headline":"AMENDMENT NO. 7","published_at":"2013-06-24","dedup_cluster_id":"","attachment_confidence":1.0,"is_primary":true,"raw_id":"c82600db2b18","form_type":"SC 13D/A","announcement_type":"","pdf_filename":"","sector":"","title":"AMENDMENT NO. 7"}],"coverage_artifacts":[]},{"event_id":"wb-co-castle-a-m-2013-03-01-1-stake-disclosure-2014-08-15-3","campaign_id":"wb-co-castle-a-m-2013-03-01-1","event_type":"stake_disclosure","event_date":"2014-08-15","actor_side":"activist","materiality_score":98,"is_material_node":true,"previous_event_id":"wb-co-castle-a-m-2013-03-01-1-stake-disclosure-2013-06-24-2","trigger_event_id":null,"artifacts":[{"artifact_id":"4f04c906663c","campaign_id":"wb-co-castle-a-m-2013-03-01-1","event_id":"wb-co-castle-a-m-2013-03-01-1-stake-disclosure-2014-08-15-3","artifact_type":"filing","event_type":"stake_disclosure","evidence_rank":"primary_filing","source_url":"https://www.sec.gov/Archives/edgar/data/0000018172/000091476014000075/c05104_sc13da10r.htm","source_name":"sec_edgar_formtype","headline":"AMENDMENT NO. 10","published_at":"2014-08-15","dedup_cluster_id":"","attachment_confidence":1.0,"is_primary":true,"raw_id":"4f04c906663c","form_type":"SC 13D/A","announcement_type":"","pdf_filename":"","sector":"","title":"AMENDMENT NO. 10"}],"coverage_artifacts":[]},{"event_id":"wb-co-castle-a-m-2013-03-01-1-stake-disclosure-2015-08-14-4","campaign_id":"wb-co-castle-a-m-2013-03-01-1","event_type":"stake_disclosure","event_date":"2015-08-14","actor_side":"activist","materiality_score":98,"is_material_node":true,"previous_event_id":"wb-co-castle-a-m-2013-03-01-1-stake-disclosure-2014-08-15-3","trigger_event_id":null,"artifacts":[{"artifact_id":"d83e9f57ed41","campaign_id":"wb-co-castle-a-m-2013-03-01-1","event_id":"wb-co-castle-a-m-2013-03-01-1-stake-disclosure-2015-08-14-4","artifact_type":"filing","event_type":"stake_disclosure","evidence_rank":"primary_filing","source_url":"https://www.sec.gov/Archives/edgar/data/0000018172/000091476015000247/a05104_sc13da12.htm","source_name":"sec_edgar_formtype","headline":"AMENDMENT NO. 12","published_at":"2015-08-14","dedup_cluster_id":"","attachment_confidence":1.0,"is_primary":true,"raw_id":"d83e9f57ed41","form_type":"SC 13D/A","announcement_type":"","pdf_filename":"","sector":"","title":"AMENDMENT NO. 12"}],"coverage_artifacts":[]},{"event_id":"wb-co-castle-a-m-2013-03-01-1-stake-disclosure-2016-02-04-5","campaign_id":"wb-co-castle-a-m-2013-03-01-1","event_type":"stake_disclosure","event_date":"2016-02-04","actor_side":"activist","materiality_score":98,"is_material_node":true,"previous_event_id":"wb-co-castle-a-m-2013-03-01-1-stake-disclosure-2015-08-14-4","trigger_event_id":null,"artifacts":[{"artifact_id":"4391a07fd4c5","campaign_id":"wb-co-castle-a-m-2013-03-01-1","event_id":"wb-co-castle-a-m-2013-03-01-1-stake-disclosure-2016-02-04-5","artifact_type":"filing","event_type":"stake_disclosure","evidence_rank":"primary_filing","source_url":"https://www.sec.gov/Archives/edgar/data/0000018172/000091476016000330/a05104_sc13da13.htm","source_name":"sec_edgar_formtype","headline":"AMENDMENT NO. 13","published_at":"2016-02-04","dedup_cluster_id":"","attachment_confidence":1.0,"is_primary":true,"raw_id":"4391a07fd4c5","form_type":"SC 13D/A","announcement_type":"","pdf_filename":"","sector":"","title":"AMENDMENT NO. 13"}],"coverage_artifacts":[]},{"event_id":"wb-co-castle-a-m-2013-03-01-1-stake-disclosure-2016-02-19-6","campaign_id":"wb-co-castle-a-m-2013-03-01-1","event_type":"stake_disclosure","event_date":"2016-02-19","actor_side":"activist","materiality_score":98,"is_material_node":true,"previous_event_id":"wb-co-castle-a-m-2013-03-01-1-stake-disclosure-2016-02-04-5","trigger_event_id":null,"artifacts":[{"artifact_id":"25fdc8093848","campaign_id":"wb-co-castle-a-m-2013-03-01-1","event_id":"wb-co-castle-a-m-2013-03-01-1-stake-disclosure-2016-02-19-6","artifact_type":"filing","event_type":"stake_disclosure","evidence_rank":"primary_filing","source_url":"https://www.sec.gov/Archives/edgar/data/0000018172/000091476016000350/a05104_sc13da14.htm","source_name":"sec_edgar_formtype","headline":"AMENDMENT NO, 14","published_at":"2016-02-19","dedup_cluster_id":"","attachment_confidence":1.0,"is_primary":true,"raw_id":"25fdc8093848","form_type":"SC 13D/A","announcement_type":"","pdf_filename":"","sector":"","title":"AMENDMENT NO, 14"}],"coverage_artifacts":[]},{"event_id":"wb-co-castle-a-m-2013-03-01-1-stake-disclosure-2016-03-29-7","campaign_id":"wb-co-castle-a-m-2013-03-01-1","event_type":"stake_disclosure","event_date":"2016-03-29","actor_side":"activist","materiality_score":98,"is_material_node":true,"previous_event_id":"wb-co-castle-a-m-2013-03-01-1-stake-disclosure-2016-02-19-6","trigger_event_id":null,"artifacts":[{"artifact_id":"dd5e34f109c9","campaign_id":"wb-co-castle-a-m-2013-03-01-1","event_id":"wb-co-castle-a-m-2013-03-01-1-stake-disclosure-2016-03-29-7","artifact_type":"filing","event_type":"stake_disclosure","evidence_rank":"primary_filing","source_url":"https://www.sec.gov/Archives/edgar/data/0000018172/000091476016000392/a05104_sc13da15.htm","source_name":"sec_edgar_formtype","headline":"AMENDMENT NO. 15","published_at":"2016-03-29","dedup_cluster_id":"","attachment_confidence":1.0,"is_primary":true,"raw_id":"dd5e34f109c9","form_type":"SC 13D/A","announcement_type":"","pdf_filename":"","sector":"","title":"AMENDMENT NO. 15"}],"coverage_artifacts":[]},{"event_id":"wb-co-castle-a-m-2013-03-01-1-stake-disclosure-2016-11-04-8","campaign_id":"wb-co-castle-a-m-2013-03-01-1","event_type":"stake_disclosure","event_date":"2016-11-04","actor_side":"activist","materiality_score":98,"is_material_node":true,"previous_event_id":"wb-co-castle-a-m-2013-03-01-1-stake-disclosure-2016-03-29-7","trigger_event_id":null,"artifacts":[{"artifact_id":"944209d9cf4c","campaign_id":"wb-co-castle-a-m-2013-03-01-1","event_id":"wb-co-castle-a-m-2013-03-01-1-stake-disclosure-2016-11-04-8","artifact_type":"filing","event_type":"stake_disclosure","evidence_rank":"primary_filing","source_url":"https://www.sec.gov/Archives/edgar/data/0000018172/000091476016000479/a74567_sc13da16.htm","source_name":"sec_edgar_formtype","headline":"AMENDMENT NO. 16","published_at":"2016-11-04","dedup_cluster_id":"","attachment_confidence":1.0,"is_primary":true,"raw_id":"944209d9cf4c","form_type":"SC 13D/A","announcement_type":"","pdf_filename":"","sector":"","title":"AMENDMENT NO. 16"}],"coverage_artifacts":[]},{"event_id":"wb-co-castle-a-m-2013-03-01-1-stake-disclosure-2016-11-14-9","campaign_id":"wb-co-castle-a-m-2013-03-01-1","event_type":"stake_disclosure","event_date":"2016-11-14","actor_side":"activist","materiality_score":98,"is_material_node":true,"previous_event_id":"wb-co-castle-a-m-2013-03-01-1-stake-disclosure-2016-11-04-8","trigger_event_id":null,"artifacts":[{"artifact_id":"fe62e2213b0b","campaign_id":"wb-co-castle-a-m-2013-03-01-1","event_id":"wb-co-castle-a-m-2013-03-01-1-stake-disclosure-2016-11-14-9","artifact_type":"filing","event_type":"stake_disclosure","evidence_rank":"primary_filing","source_url":"https://www.sec.gov/Archives/edgar/data/0000018172/000091476016000487/a05104_sc13da17.htm","source_name":"sec_edgar_formtype","headline":"AMENDMENT NO. 17","published_at":"2016-11-14","dedup_cluster_id":"","attachment_confidence":1.0,"is_primary":true,"raw_id":"fe62e2213b0b","form_type":"SC 13D/A","announcement_type":"","pdf_filename":"","sector":"","title":"AMENDMENT NO. 17"}],"coverage_artifacts":[]},{"event_id":"wb-co-castle-a-m-2013-03-01-1-stake-disclosure-2016-12-21-10","campaign_id":"wb-co-castle-a-m-2013-03-01-1","event_type":"stake_disclosure","event_date":"2016-12-21","actor_side":"activist","materiality_score":98,"is_material_node":true,"previous_event_id":"wb-co-castle-a-m-2013-03-01-1-stake-disclosure-2016-11-14-9","trigger_event_id":null,"artifacts":[{"artifact_id":"b2db482238dd","campaign_id":"wb-co-castle-a-m-2013-03-01-1","event_id":"wb-co-castle-a-m-2013-03-01-1-stake-disclosure-2016-12-21-10","artifact_type":"filing","event_type":"stake_disclosure","evidence_rank":"primary_filing","source_url":"https://www.sec.gov/Archives/edgar/data/0000018172/000091476016000503/a05104_sc13da18.htm","source_name":"sec_edgar_formtype","headline":"AMENDMENT NO. 18","published_at":"2016-12-21","dedup_cluster_id":"","attachment_confidence":1.0,"is_primary":true,"raw_id":"b2db482238dd","form_type":"SC 13D/A","announcement_type":"","pdf_filename":"","sector":"","title":"AMENDMENT NO. 18"}],"coverage_artifacts":[]}],"coverage_artifacts":[],"low_trust_artifacts":[]}