{"campaign_id":"steel-connect-inc-boom-2024-06-13-1","events":[{"event_id":"steel-connect-inc-boom-2024-06-13-1-stake-disclosure-2024-06-13-1","campaign_id":"steel-connect-inc-boom-2024-06-13-1","event_type":"stake_disclosure","event_date":"2024-06-13","actor_side":"activist","materiality_score":98,"is_material_node":true,"previous_event_id":null,"trigger_event_id":null,"artifacts":[{"artifact_id":"d0d721065b8a","campaign_id":"steel-connect-inc-boom-2024-06-13-1","event_id":"steel-connect-inc-boom-2024-06-13-1-stake-disclosure-2024-06-13-1","artifact_type":"filing","event_type":"stake_disclosure","evidence_rank":"primary_filing","source_url":"https://www.sec.gov/Archives/edgar/data/34067/000092189524001414/ex991tosc13d04197092_061324.pdf","source_name":"sec_edgar_exhibit","headline":"EX-99 Exhibit \u2014 DMC Global Inc.","published_at":"2024-06-13","dedup_cluster_id":"","attachment_confidence":1.0,"is_primary":true,"raw_id":"d0d721065b8a","form_type":"SC 13D","announcement_type":"","pdf_filename":"","blob_url":"","sector":"","title":"EX-99 Exhibit \u2014 DMC Global Inc."},{"artifact_id":"9810ebab961d","campaign_id":"steel-connect-inc-boom-2024-06-13-1","event_id":"steel-connect-inc-boom-2024-06-13-1-stake-disclosure-2024-06-13-1","artifact_type":"filing","event_type":"stake_disclosure","evidence_rank":"primary_filing","source_url":"https://www.sec.gov/Archives/edgar/data/0000034067/000092189524001414/sc13d04197092_06132024.htm","source_name":"sec_edgar_formtype","headline":"THE SCHEDULE 13D","published_at":"2024-06-13","dedup_cluster_id":"","attachment_confidence":1.0,"is_primary":true,"raw_id":"9810ebab961d","form_type":"SC 13D","announcement_type":"","pdf_filename":"","blob_url":"","sector":"","title":"THE SCHEDULE 13D"}],"coverage_artifacts":[]},{"event_id":"steel-connect-inc-boom-2024-06-13-1-stake-disclosure-2024-09-17-2","campaign_id":"steel-connect-inc-boom-2024-06-13-1","event_type":"stake_disclosure","event_date":"2024-09-17","actor_side":"activist","materiality_score":98,"is_material_node":true,"previous_event_id":"steel-connect-inc-boom-2024-06-13-1-stake-disclosure-2024-06-13-1","trigger_event_id":null,"artifacts":[{"artifact_id":"f95af27c7817","campaign_id":"steel-connect-inc-boom-2024-06-13-1","event_id":"steel-connect-inc-boom-2024-06-13-1-stake-disclosure-2024-09-17-2","artifact_type":"filing","event_type":"stake_disclosure","evidence_rank":"primary_filing","source_url":"https://www.sec.gov/Archives/edgar/data/0000034067/000092189524002136/sc13da104197092_09172024.htm","source_name":"sec_edgar_formtype","headline":"AMENDMENT NO. 1 TO THE SCHEDULE 13D","published_at":"2024-09-17","dedup_cluster_id":"","attachment_confidence":1.0,"is_primary":true,"raw_id":"f95af27c7817","form_type":"SC 13D/A","announcement_type":"","pdf_filename":"","blob_url":"","sector":"","title":"AMENDMENT NO. 1 TO THE SCHEDULE 13D"}],"coverage_artifacts":[]},{"event_id":"steel-connect-inc-boom-2024-06-13-1-stake-disclosure-2024-11-13-3","campaign_id":"steel-connect-inc-boom-2024-06-13-1","event_type":"stake_disclosure","event_date":"2024-11-13","actor_side":"activist","materiality_score":98,"is_material_node":true,"previous_event_id":"steel-connect-inc-boom-2024-06-13-1-stake-disclosure-2024-09-17-2","trigger_event_id":null,"artifacts":[{"artifact_id":"154fb9b8e1db","campaign_id":"steel-connect-inc-boom-2024-06-13-1","event_id":"steel-connect-inc-boom-2024-06-13-1-stake-disclosure-2024-11-13-3","artifact_type":"filing","event_type":"stake_disclosure","evidence_rank":"primary_filing","source_url":"https://www.sec.gov/Archives/edgar/data/0000034067/000092189524002643/sc13da204197092_11132024.htm","source_name":"sec_edgar_formtype","headline":"AMENDMENT NO. 2 TO THE SCHEDULE 13D","published_at":"2024-11-13","dedup_cluster_id":"","attachment_confidence":1.0,"is_primary":true,"raw_id":"154fb9b8e1db","form_type":"SC 13D/A","announcement_type":"","pdf_filename":"","blob_url":"","sector":"","title":"AMENDMENT NO. 2 TO THE SCHEDULE 13D"}],"coverage_artifacts":[]}],"coverage_artifacts":[],"low_trust_artifacts":[]}